consoles/__init__.py
consoles/cts.py
consoles/daktronics.py
consoles/sports.py
consoles/util.py
consoles/debugger/__init__.py
consoles/debugger/cts.py
consoles/debugger/daktronics.py
scorebox_consoles-1.2.0.dist-info/LICENSE
scorebox_consoles-1.2.0.dist-info/METADATA
scorebox_consoles-1.2.0.dist-info/WHEEL
scorebox_consoles-1.2.0.dist-info/top_level.txt
scorebox_consoles-1.2.0.dist-info/RECORD
