Metadata-Version: 2.1
Name: scorebox-consoles
Version: 1.2.0
Summary: Python interface for scoreboard consoles manufactured by Daktronics and Colorado Time Systems
Home-page: https://github.com/FlantasticDan/scorebox-consoles
Author: Daniel Flanagan
License: UNKNOWN
Project-URL: Bug Tracker, https://github.com/FlantasticDan/scorebox-consoles/issues
Platform: UNKNOWN
Classifier: Programming Language :: Python :: 3
Classifier: License :: OSI Approved :: MIT License
Classifier: Operating System :: OS Independent
Requires-Python: >=3.9
License-File: LICENSE
Requires-Dist: pyserial
